flat_world/AbstractActuator.py
flat_world/AbstractEnvEntity.py
flat_world/AbstractEnvState.py
flat_world/ActuatorType.py
flat_world/AgentColoring.py
flat_world/AgentState.py
flat_world/BaseEnvCharacter.py
flat_world/BoosterActuator.py
flat_world/DefaultActuator.py
flat_world/DualActuator.py
flat_world/EnvState.py
flat_world/FlatWorldConfig.py
flat_world/FlatWorldElement.py
flat_world/FlatWorldEnvironment.py
flat_world/FlatWorldMultiAgentConfig.py
flat_world/PredatorLevel.py
flat_world/PredatorState.py
flat_world/PushException.py
flat_world/artifacts/ayar.ttf
flat_world/helpers/ObservationScaler.py
flat_world/helpers/PrecalculatedOrientations.py
flat_world/helpers/WeightedHuberLoss.py
flat_world/helpers/WeightedMSELoss.py
flat_world/helpers/batch_math_helper.py
flat_world/helpers/math_helper.py
flat_world/helpers/reward_helper.py
flat_world/ref_agents/AbstractAgent.py
flat_world/ref_agents/AbstractAutonomousAgent.py
flat_world/ref_agents/DualCNN.py
flat_world/ref_agents/RandomAgent.py
flat_world/ref_agents/SimpleCNNAgent.py
flat_world/tasks/all_env_elements_config.py
flat_world/tasks/blank_config.py
flat_world/tasks/challenge_1_config.py
flat_world/tasks/challenge_2_config.py
flat_world/tasks/demo_config.py
flat_world/tasks/food_wall_config.py
flat_world/tasks/generic_config.py
flat_world/tasks/memory_config.py
flat_world/tasks/one_brick_config.py
flat_world/tasks/one_fence_config.py
flat_world/tasks/one_translucent_fence_config.py
flat_world/tasks/simple_food_2_config.py
flat_world/tasks/simple_food_config.py
flat_world/tasks/starter_1_config.py
flat_world/tasks/starter_2_config.py
flat_world/tasks/two_translucent_fences_config.py
flat_world/tasks/multi_agent/big_grid_config.py
flat_world/tasks/multi_agent/food_for_all_config.py
flat_world/tasks/multi_agent/multiagent_all_config.py
flat_world/tasks/multi_agent/multiagent_blank_config.py
flat_world/tasks/multi_agent/multiagent_box_config.py
flat_world/tasks/multi_agent/three_agents_and_a_predator_config.py
flat_world-0.9.3.dist-info/METADATA
flat_world-0.9.3.dist-info/WHEEL
flat_world-0.9.3.dist-info/top_level.txt
flat_world-0.9.3.dist-info/RECORD
