Metadata-Version: 2.1
Name: flat-world
Version: 0.9.3
Summary: A text memory meant to be used with conversational language models.
Home-page: https://github.com/goodai-jose-solorzano/FlatWorld
Requires-Dist: torch
Requires-Dist: pytest
Requires-Dist: gym
Requires-Dist: numpy
Requires-Dist: tk
Requires-Dist: Pillow
